slfortigate-0.1.3.dist-info/RECORD
slfortigate-0.1.3.dist-info/WHEEL
slfortigate-0.1.3.dist-info/METADATA
slfortigate-0.1.3.dist-info/top_level.txt
slfortigate-0.1.3.dist-info/metadata.json
slfortigate-0.1.3.dist-info/entry_points.txt
slfortigate-0.1.3.dist-info/DESCRIPTION.rst
slfortigate-0.1.3.dist-info/pbr.json
slfortigate/configure.py
slfortigate/cli.py
slfortigate/__init__.py
slfortigate/test/__init__.py
slfortigate/test/unit/test_main.py
slfortigate/test/unit/__init__.py
slfortigate/test/integration/int_test_configure_fortigate_tests.py
slfortigate/test/integration/__init__.py
