Metadata-Version: 2.0
Name: slfortigate
Version: 0.1.3
Summary: Scripts to order a Fortigate from Softlayer and lock it down
Home-page: UNKNOWN
Author: bruce potter
Author-email: bp@us.ibm.com
License: EPL-1.0
Keywords: setup
Requires-Dist: pexpect (==3.3)
Requires-Dist: SoftLayer (==4.0.1)
Requires-Dist: requests[security] (==2.7.0)
